biologreen/__init__.py
biologreen/client.py
biologreen/schemas.py
biologreen/utils.py
biologreen-0.1.0.dist-info/METADATA
biologreen-0.1.0.dist-info/WHEEL
biologreen-0.1.0.dist-info/top_level.txt
biologreen-0.1.0.dist-info/RECORD
