Metadata-Version: 2.4
Name: biologreen
Version: 0.1.0
Summary: The official Python SDK for the Bio-Logreen Facial Authentication API.
Home-page: https://github.com/AtuhurraSolomon/biologreen-python-sdk
Author: AtuhurraSolomon
Author-email: atuhurrasolomon47@gmail.com
Classifier: Programming Language :: Python :: 3
Classifier: License :: OSI Approved :: MIT License
Classifier: Operating System :: OS Independent
Requires-Python: >=3.8
Requires-Dist: requests>=2.20.0
Requires-Dist: pydantic>=2.0.0
Dynamic: author
Dynamic: author-email
Dynamic: classifier
Dynamic: description
Dynamic: description-content-type
Dynamic: home-page
Dynamic: requires-dist
Dynamic: requires-python
Dynamic: summary
